harvest_rs/__init__.py
harvest_rs/__init__.pyi
harvest_rs/harvest_rs.cpython-313-x86_64-linux-gnu.so
harvest_rs/py.typed
harvest_rs-0.0.1.dist-info/METADATA
harvest_rs-0.0.1.dist-info/WHEEL
harvest_rs-0.0.1.dist-info/RECORD
