Metadata-Version: 2.4
Name: harvest_rs
Version: 0.0.1
Requires-Dist: numpy>=1.20
Requires-Python: >=3.8
